ransomwatch/__init__.py
ransomwatch/__main__.py
ransomwatch/api.py
ransomwatch/cli.py
ransomwatch/config.py
ransomwatch/logic.py
ransomwatch/utils.py
ransomwatch-1.2.3.dist-info/licenses/LICENSE
ransomwatch-1.2.3.dist-info/METADATA
ransomwatch-1.2.3.dist-info/WHEEL
ransomwatch-1.2.3.dist-info/entry_points.txt
ransomwatch-1.2.3.dist-info/top_level.txt
ransomwatch-1.2.3.dist-info/RECORD
