Metadata-Version: 2.4
Name: ransomwatch
Version: 1.2.3
Summary: Ransomware Intelligence Tool - Designed for threat intelligence, security research, and situational awareness
Author-email: Yannick Boog <security@yannick.xyz>
License: MIT
Project-URL: Homepage, https://github.com/yannickboog/ransomwatch
Project-URL: Bug Reports, https://github.com/yannickboog/ransomwatch/issues
Project-URL: Source, https://github.com/yannickboog/ransomwatch
Keywords: ransomware,security,threat-intelligence,cybersecurity
Classifier: Development Status :: 4 - Beta
Classifier: Intended Audience :: Information Technology
Classifier: Intended Audience :: System Administrators
Classifier: License :: OSI Approved :: MIT License
Classifier: Operating System :: OS Independent
Classifier: Programming Language :: Python :: 3
Classifier: Programming Language :: Python :: 3.8
Classifier: Programming Language :: Python :: 3.9
Classifier: Programming Language :: Python :: 3.10
Classifier: Programming Language :: Python :: 3.11
Classifier: Programming Language :: Python :: 3.12
Classifier: Topic :: Security
Classifier: Topic :: System :: Monitoring
Requires-Python: >=3.8
License-File: LICENSE
Requires-Dist: requests>=2.31.0
Requires-Dist: urllib3>=1.26.0
Provides-Extra: dev
Requires-Dist: black>=21.0; extra == "dev"
Requires-Dist: flake8>=3.8; extra == "dev"
Dynamic: license-file
